snotra/__init__.py
snotra/core.py
snotra/delete.py
snotra/future.py
snotra/codebooks/atc_2015_eng.csv
snotra/codebooks/atc_2018_no_from difi.csv
snotra/codebooks/atc_20xx_eng_long.csv
snotra/codebooks/drg_200x_no.csv
snotra/codebooks/icd10cm_pcs_2017_eng.csv
snotra/codebooks/ncmp_ncsp_ncrp_2017_no.csv
snotra/codebooks/normaltariffen_20xx_no.csv
snotra/codebooks/special_20xx_no.csv
snotra/data/encounters.csv
snotra/data/event_codebook.csv
snotra/data/events_test_data.csv
snotra/data/medications.csv
snotra/data/patients.csv
snotra/data/procedure_codebook.csv
snotra/data/procedures.csv
snotra-0.0.9.dist-info/METADATA
snotra-0.0.9.dist-info/RECORD
snotra-0.0.9.dist-info/WHEEL
snotra-0.0.9.dist-info/top_level.txt
