Metadata-Version: 2.1
Name: snotra
Version: 0.0.9
Summary: Tool to analyze data on hospital events, prescriptions and similar types of health data
Home-page: UNKNOWN
Author: Hans Olav Melberg
Author-email: hans.melberg@gmail.com
License: MIT
Keywords: health pandas
Platform: UNKNOWN
